siebel/__init__.py
siebel/maintenance/__init__.py
siebel/maintenance/crash.py
siebel_crash_report-0.1.0.data/scripts/crash_reporter
siebel_crash_report-0.1.0.dist-info/LICENSE
siebel_crash_report-0.1.0.dist-info/METADATA
siebel_crash_report-0.1.0.dist-info/WHEEL
siebel_crash_report-0.1.0.dist-info/top_level.txt
siebel_crash_report-0.1.0.dist-info/RECORD
