Metadata-Version: 2.1
Name: siebel-crash-report
Version: 0.1.0
Summary: Searchs and aggregates Siebel component crashes information into a nice report.
Home-page: https://github.com/glasswalk3r/siebel-crash-report
Author: Alceu Rodrigues de Freitas Junior
Author-email: arfreitas@cpan.org
License: UNKNOWN
Keywords: Siebel crash core dump component
Platform: UNKNOWN
Classifier: Programming Language :: Python :: 3
Classifier: Programming Language :: Python :: 3.6
Classifier: Programming Language :: Python :: 3.7
Classifier: Programming Language :: Python :: 3.8
Classifier: Programming Language :: Python :: 3.9
Classifier: Operating System :: POSIX :: Linux
Classifier: Development Status :: 5 - Production/Stable
Classifier: Intended Audience :: Developers
Classifier: Intended Audience :: System Administrators
Classifier: License :: OSI Approved :: GNU General Public License v3 (GPLv3)
License-File: LICENSE
Requires-Dist: simplejson (>=3.17.2)
Requires-Dist: pyyaml (>=5.4)
